mrkwatkins/oakemuai/__init__.py
mrkwatkins/oakemuai/assemblies/MrKWatkins.OakEmu.Machines.ZXSpectrum.AI.dll
mrkwatkins/oakemuai/assemblies/VYaml.Annotations.dll
mrkwatkins/oakemuai/assemblies/VYaml.dll
mrkwatkins/oakemuai/gymnasium/__init__.py
mrkwatkins/oakemuai/gymnasium/game_configuration.py
mrkwatkins/oakemuai/gymnasium/oakemu_env.py
mrkwatkins/oakemuai/gymnasium/observation_configuration.py
mrkwatkins/oakemuai/gymnasium/registration.py
mrkwatkins/oakemuai/image/__init__.py
mrkwatkins/oakemuai/image/image.py
mrkwatkins/oakemuai/image/types.py
mrkwatkins/oakemuai/ray/__init__.py
mrkwatkins/oakemuai/ray/recording_callbacks.py
mrkwatkins/oakemuai/ray/registration.py
mrkwatkins/oakemuai/ui/__init__.py
mrkwatkins/oakemuai/ui/ui.py
mrkwatkins_oakemuai-0.0.2.dist-info/LICENCE
mrkwatkins_oakemuai-0.0.2.dist-info/METADATA
mrkwatkins_oakemuai-0.0.2.dist-info/WHEEL
mrkwatkins_oakemuai-0.0.2.dist-info/RECORD
