Metadata-Version: 2.1
Name: mrkwatkins-oakemuai
Version: 0.0.2
Summary: AI extensions for mrkwatkins.oakemu.
Home-page: https://www.mrkwatkins.co.uk
License: MIT
Author: MrKWatkins
Author-email: mrkwatkins@gmail.com
Requires-Python: >=3.11,<3.13
Classifier: Development Status :: 3 - Alpha
Classifier: License :: OSI Approved :: MIT License
Classifier: Programming Language :: Python :: 3
Classifier: Programming Language :: Python :: 3.11
Classifier: Programming Language :: Python :: 3.12
Requires-Dist: gymnasium (==1.1.1)
Requires-Dist: mrkwatkins-oakemu (>=0.0.16,<0.0.17)
Requires-Dist: opencv-python (>=4.11.0.86,<5.0.0.0)
Requires-Dist: pandas (>=2.2.3,<3.0.0)
Requires-Dist: pyarrow (>=19.0.0,<20.0.0)
Requires-Dist: pygame (>=2.6.1,<3.0.0)
Requires-Dist: pythonnet (>=3.0.5,<4.0.0)
Requires-Dist: ray[default] (>=2.44.1,<3.0.0)
Project-URL: Repository, https://github.com/MrKWatkins/OakEmu-AI
